wal_iot/__init__.py
wal_iot/lib.py
wal_iot-0.2.0.dist-info/METADATA
wal_iot-0.2.0.dist-info/WHEEL
wal_iot-0.2.0.dist-info/RECORD
